ftmcellebrite/__init__.py
ftmcellebrite/cellebrite.py
ftmcellebrite/cli.py
ftmcellebrite/util.py
followthemoney_cellebrite-0.1.0.dist-info/LICENSE
followthemoney_cellebrite-0.1.0.dist-info/METADATA
followthemoney_cellebrite-0.1.0.dist-info/WHEEL
followthemoney_cellebrite-0.1.0.dist-info/entry_points.txt
followthemoney_cellebrite-0.1.0.dist-info/namespace_packages.txt
followthemoney_cellebrite-0.1.0.dist-info/top_level.txt
followthemoney_cellebrite-0.1.0.dist-info/RECORD
