Metadata-Version: 2.1
Name: followthemoney-cellebrite
Version: 0.1.0
Summary: UNKNOWN
Home-page: UNKNOWN
Author: Organized Crime and Corruption Reporting Project
Author-email: data@occrp.org
License: MIT
Platform: UNKNOWN
Requires-Dist: followthemoney (>=1.29.5)
